aelf_api_client/__init__.py
aelf_api_client/client.py
aelf_api_client/schemas/__init__.py
aelf_api_client/schemas/complines.py
aelf_api_client/schemas/enums/__init__.py
aelf_api_client/schemas/enums/color.py
aelf_api_client/schemas/enums/entity.py
aelf_api_client/schemas/enums/zone.py
aelf_api_client/schemas/informations.py
aelf_api_client/schemas/lauds.py
aelf_api_client/schemas/mass.py
aelf_api_client/schemas/none.py
aelf_api_client/schemas/reading.py
aelf_api_client/schemas/readings.py
aelf_api_client/schemas/responses/__init__.py
aelf_api_client/schemas/responses/complines.py
aelf_api_client/schemas/responses/informations.py
aelf_api_client/schemas/responses/lauds.py
aelf_api_client/schemas/responses/masses.py
aelf_api_client/schemas/responses/none.py
aelf_api_client/schemas/responses/readings.py
aelf_api_client/schemas/responses/sext.py
aelf_api_client/schemas/responses/terce.py
aelf_api_client/schemas/responses/vespers.py
aelf_api_client/schemas/sext.py
aelf_api_client/schemas/terce.py
aelf_api_client/schemas/text.py
aelf_api_client/schemas/vespers.py
aelf_api_client-1.3.5.dist-info/METADATA
aelf_api_client-1.3.5.dist-info/WHEEL
aelf_api_client-1.3.5.dist-info/licenses/LICENSE
aelf_api_client-1.3.5.dist-info/RECORD
