Metadata-Version: 2.4
Name: aelf-api-client
Version: 1.3.5
Summary: Python client for the AELF API (https://api.aelf.org/)
License-Expression: MIT
License-File: LICENSE
Author: Thamin
Author-email: github@thamin.ovh
Requires-Python: >=3.13
Classifier: Programming Language :: Python :: 3
Classifier: Operating System :: OS Independent
Requires-Dist: aiohttp (>=3.0.0,<4.0.0)
Requires-Dist: async-timeout (>=4.0.0)
Requires-Dist: pydantic (>=2.0.0,<3.0.0)
Project-URL: Homepage, https://github.com/thamin-i/aelf-api-client
Project-URL: Issues, https://github.com/thamin-i/aelf-api-client/issues
